ipyscore/__init__.py
ipyscore/widget.py
ipyscore/static/index.js
ipyscore-0.2.0.dist-info/METADATA
ipyscore-0.2.0.dist-info/WHEEL
ipyscore-0.2.0.dist-info/licenses/LICENSE.txt
ipyscore-0.2.0.dist-info/RECORD
