Metadata-Version: 2.1
Name: ipyscore
Version: 0.2.0
Summary: A Jupyter widget for rendering music notation
Project-URL: Homepage, https://github.com/davidbrochart/ipyscore
Author-email: David Brochart <david.brochart@gmail.com>
License: Copyright (c) 2023 David Brochart
License-File: LICENSE.txt
Keywords: IPython,Jupyter,Widgets
Classifier: Framework :: Jupyter
Classifier: Intended Audience :: Developers
Classifier: Intended Audience :: Science/Research
Classifier: License :: OSI Approved :: BSD License
Classifier: Programming Language :: Python
Classifier: Programming Language :: Python :: 3
Classifier: Programming Language :: Python :: 3.7
Classifier: Programming Language :: Python :: 3.8
Classifier: Programming Language :: Python :: 3.9
Classifier: Programming Language :: Python :: 3.10
Requires-Python: >=3.7
Requires-Dist: anywidget<1,>=0.6.3
